wsgi_proxy/__init__.py
wsgi_proxy/cli.py
wsgi_proxy/version.py
wsgi_proxy-0.4.0.dist-info/DESCRIPTION.rst
wsgi_proxy-0.4.0.dist-info/METADATA
wsgi_proxy-0.4.0.dist-info/RECORD
wsgi_proxy-0.4.0.dist-info/WHEEL
wsgi_proxy-0.4.0.dist-info/entry_points.txt
wsgi_proxy-0.4.0.dist-info/metadata.json
wsgi_proxy-0.4.0.dist-info/top_level.txt
