Metadata-Version: 2.0
Name: wsgi-proxy
Version: 0.4.0
Summary: WSGI proxy application
Home-page: https://bitbucket.org/dahlia/wsgi-proxy
Author: Hong Minhee
Author-email: minhee@dahlia.kr
License: Apache License 2.0
Platform: Any
Classifier: Development Status :: 4 - Beta
Classifier: Environment :: Console
Classifier: Intended Audience :: Developers
Classifier: License :: OSI Approved :: Apache Software License
Classifier: Operating System :: OS Independent
Classifier: Topic :: Software Development :: Libraries :: Python Modules
Requires-Dist: six
Requires-Dist: waitress (>=0.8.2)
